Metadata-Version: 2.1
Name: hgftg
Version: 1.9
Summary: This PIP only made for designing Tool and Termux Bennar
Home-page: https://github.com/cracker911181/cracker_say
Author: cracker911181
License-File: LICENSE
